netztransparenz/__init__.py
netztransparenz/base_client.py
netztransparenz/client.py
netztransparenz/constants.py
netztransparenz/dienstleistungen_client.py
netztransparenz/hochrechnung_client.py
netztransparenz/nrvsaldo_client.py
netztransparenz/vermarktung_client.py
netztransparenz-0.2.3.dist-info/licenses/LICENSES/AGPL-3.0-or-later.txt
netztransparenz-0.2.3.dist-info/METADATA
netztransparenz-0.2.3.dist-info/WHEEL
netztransparenz-0.2.3.dist-info/top_level.txt
netztransparenz-0.2.3.dist-info/RECORD
