Metadata-Version: 2.4
Name: netztransparenz
Version: 0.2.3
Summary: A simple client to acess data from the German Netztransparenz portal
Author-email: Marvin Lorber <lorber@fh-aachen.de>
License-Expression: AGPL-3.0-or-later
Project-URL: Homepage, https://github.com/ma-lor/NetztransparenzClient
Project-URL: Issues, https://github.com/ma-lor/NetztransparenzClient/issues
Classifier: Programming Language :: Python :: 3
Classifier: Operating System :: OS Independent
Requires-Python: >=3.10
License-File: LICENSES/AGPL-3.0-or-later.txt
Requires-Dist: pandas>=2.3.2
Requires-Dist: requests>=2.32.5
Dynamic: license-file
